Workbook
Name ADDRESS: #REF!
Name AddressLine1: 'Input Form'!$B$4
Name AddressLine2: 'Input Form'!$B$5
Name AddressLine3: 'Input Form'!$B$6
Name BasicPackage: 'Input Form'!$A$19
Name BasicPackagePrice: 'Input Form'!$B$19
Name CompanyName: 'Input Form'!$B$3
Name CUSTOMER: #REF!
Name CustomerName: 'Input Form'!$B$2
Name DE: #REF!
Name MenuPackage1: 'Input Form'!$A$20
Name MenuPackage1Price: 'Input Form'!$B$20
Name MenuPackage2: 'Input Form'!$A$21
Name MenuPackage2Price: 'Input Form'!$B$21
Name MenuPackage3: 'Input Form'!$A$22
Name MenuPackage3Price: 'Input Form'!$B$22
Name MenuPackage4: 'Input Form'!$A$23
Name MenuPackagePrice4: 'Input Form'!$B$23

Sheet Input Form
A1: CUSTOMER INFORMATION
A2: Customer Name | B2: Evan Dailey
A3: Company Name | B3: Express Car Wash
A4: Address Line 1
A5: Address Line 2 | B5: 231 MacCorkle Ave SW
A6: Address Line 3 | B6: South Charleston, WV 25303
A8: Weekly Hours of Operation | B8: Average Daily Wash Hours
A9: 84 | B9: =A9/7 -> 12
A11: LABOR
A12: Position | B12: Labor Hours | C12: Hourly Wages | D12: Burden Rate
A13: Manager | B13: 49 | C13: 25 | D13: 0.2
A14: Assistant Manager | B14: 42 | C14: 20 | D14: 0.2
A15: Attendants | B15: 160 | C15: 12 | D15: 0.2
A17: WASH PACKAGES
A18: Packages | B18: Price | C18: Chemical Costs | D18: % of Customers
A19: Basic Package | B19: 5 | C19: 0.45 | D19: 0.65
A20: Menu Package #1 | B20: 10 | C20: 0.886 | D20: 0.15
A21: Menu Package #2 | B21: 15 | C21: 1.054 | D21: 0.12
A22: Menu Package #3 | B22: 20 | C22: 1.873 | D22: 0.04
A23: Menu Package #4 | B23: 25 | C23: 2.121 | D23: 0.04
A25: WASH PACKAGE CHANGES - YEAR 2 THROUGH YEAR 5
A26: Packages | B26: Year 2 Price | C26: Year 3 Price | D26: Year 4 Price | E26: Year 5 Price
A27: Basic Package | B27: 5 | C27: 5 | D27: 5 | E27: 5
A28: Menu Package #1 | B28: 10 | C28: 10 | D28: 10 | E28: 10
A29: Menu Package #2 | B29: 15 | C29: 15 | D29: 15 | E29: 15
A30: Menu Package #3 | B30: 20 | C30: 20 | D30: 20 | E30: 20
A31: Menu Package #4 | B31: 25 | C31: 25 | D31: 25 | E31: 25
A33: SITE - SPECIFIC FACTORS
A34: Area Profile | B34: Shopping | C34: Business | D34: Residential | E34: Industrial | F34: Site Score
C35: 1 | F35: =IF(B35=1,0.15,IF(C35=1,0.1,IF(D35=1,0.05,IF(E35=1,-0.25,0)))) -> 0.1
A36: Nearest Competition | B36: One in 4 Miles | C36: Multiple in 4 Miles | D36: One in 2 Miles | E36: Multiple in 2 Miles | F36: Site Score
C37: 1 | F37: =IF(B37=1,0.15,IF(C37=1,0.125,IF(D37=1,0.075,IF(E37=1,-0.025,0)))) -> 0.125
A38: Weekly Hours of Operation | B38: More Than 70 Hours | C38: 65 - 70 Hours | D38: 60 - 64 Hours | E38: Less Than 60 Hours | F38: Site Score
B39: 1 | F39: =IF(B39=1,0.15,IF(C39=1,0.1,IF(D39=1,0.025,IF(E39=1,0,0)))) -> 0.15
A40: Type of Site | B40: Corner Lot With Light | C40: Corner Lot Without Light | D40: Inside Lot Near Light | E40: Inside Lot No Light | F40: Site Score
B41: 1 | F41: =IF(B41=1,0.15,IF(C41=1,0.125,IF(D41=1,0.075,IF(E41=1,0.05,0)))) -> 0.15
A42: Site Accessibility | B42: Easy In & Easy Out | C42: Easy In/Out With Divided Highway | D42: Easy In Or Easy Out One Way | E42: Difficult In and Out | F42: Site Score
B43: 1 | F43: =IF(B43=1,0.15,IF(C43=1,0.1,IF(D43=1,0.05,IF(E43=1,0,0)))) -> 0.15
A44: Entrance Stack Up Area | B44: More Than 20 Vehicles | C44: 20 - 15 Vehicles | D44: 14 - 10 Vehicles | E44: Less Than 10 Vehicles | F44: Site Score
C45: 1 | F45: =IF(B45=1,0.15,IF(C45=1,0.125,IF(D45=1,0.075,IF(E45=1,0.05,0)))) -> 0.125
A46: Number of Free Vacuum Slots | B46: More Than 20 Vehicles | C46: 12 - 20 Vehicles | D46: Less Than 12 Vehicles | E46: Coin or None | F46: Site Score
C47: 1 | F47: =IF(B47=1,0.15,IF(C47=1,0.1,IF(D47=1,0.05,IF(E47=1,-0.25,0)))) -> 0.1
A48: Number of Pay Stations | B48: 3 or More | C48: 2 | D48: 1 | E48: Live Person | F48: Site Score
C49: 1 | F49: =IF(B49=1,0.15,IF(C49=1,0.1,IF(D49=1,0.05,IF(E49=1,0,0)))) -> 0.1
A50: Visibility | B50: More Than 500 Feet Both Directions | C50: 400 - 500 Feet Both Directions | D50: 300 - 400 Feet Both Directions | E50: Less Than 300 Feet Both Directions | F50: Site Score
B51: 1 | F51: =IF(B51=1,0.15,IF(C51=1,0.1,IF(D51=1,0.05,IF(E51=1,0,0)))) -> 0.15
A52: Traffic Speed | B52: Less Than 30 MPH | C52: 30 - 40 MPH | D52: 40 - 50 MPH | E52: More Than 50 MPH | F52: Site Score
D53: 1 | F53: =IF(B53=1,0.15,IF(C53=1,0.1,IF(D53=1,0.05,IF(E53=1,0,0)))) -> 0.05
A54: CUMULATIVE SITE SCORE: | F54: =F35+F37+F39+F41+F43+F45+F47+F49+F51+F53 -> 1.2
A56: DEMOGRAPHIC COMPONENTS
A57: AVERAGE HOUSEHOLD SIZE (TARGET SIZE: 2.1) | E57: 2.2 | F57: =IF(E57<2.101,-0.1*(2.1-E57),IF(E57>3,-0.5*(E57-3),0)) -> 0
A58: % of POPULATION 25 TO 65 (TARGET: 55%) | E58: 0.492 | F58: =-0.3*(0.55-E58) -> -0.0174
A59: % OF HOUSEHOLDS WITH INCOMES > $35,000 (TARGET: 50%) | E59: 0.621 | F59: =-0.75*(0.5-E59) -> 0.09075
A60: BASE PRICE OF CAR WASH | E60: 5 | F60: =IF(E60<5.01,0.5*(5-E60),-0.075*(E60-5)) -> 0
A61: CUMULATIVE DEMOGRAPHIC SCORE | F61: =SUM(F57:F60)/4 -> 0.0183375
A63: SITE SCORES
A64: FIRST YEAR - START UP - TARGET SCORE | F64: =(F54*0.7)*(1+F61)/85 -> 0.010063571
A65: SECOND YEAR TARGET SCORE | F65: =$F$54*(1+$F$61)/92 -> 0.013282663
A66: MATURE TARGET SCORE | F66: =$F$54*(1+$F$61)/76 -> 0.016079013
A68: TRAFFIC COUNT AND PROJECTED TRAFFIC INCREASES
A69: Traffic Count | B69: Year 3 Increase | C69: Year 4 Increase | D69: Year 5 Increase
A70: 19504 | B70: 0 | C70: 0 | D70: 0
A72: CAR WASH VOLUME ESTIMATES
B73: YEAR 1 | C73: YEAR 2 | D73: YEAR 3 | E73: YEAR 4 | F73: YEAR 5
A74: Yearly | B74: =F64*A70*300 -> 58883.964 | C74: =F65*A70*300 -> 77719.518 | D74: =($F$54*(1+$F$61))/85*($A$70*(1+B$70))*300 -> 84119.949 | E74: =($F$54*(1+$F$61))/82*($A$70*(1+C$70))*300 -> 87197.508 | F74: =F66*(A70*(1+D70)*300) -> 94081.522
A75: Monthly | B75: =B74/12 -> 4906.997 | C75: =C74/12 -> 6476.6265 | D75: =D74/12 -> 7009.9957 | E75: =E74/12 -> 7266.459 | F75: =F74/12 -> 7840.1268
A76: Max Daily | B76: =B75/4.5/7*3 -> 467.33305 | C76: =C75/4.5/7*3 -> 616.82157 | D76: =D75/4.5/7*3 -> 667.61864 | E76: =E75/4.5/7*3 -> 692.04371 | F76: =F75/4.5/7*3 -> 746.67874
A77: Max Hourly | B77: =IFERROR((B76/$B9*1.3),0) -> 50.627747 | C77: =IFERROR((C76/$B9*1.3),0) -> 66.822337 | D77: =IFERROR((D76/$B9*1.3),0) -> 72.325353 | E77: =IFERROR((E76/$B9*1.3),0) -> 74.971402 | F77: =IFERROR((F76/$B9*1.3),0) -> 80.890197
A79: CAR WASH ACQUISITION BUDGET
A80: Investment Item | B80: Total Investment | C80: % Owner Investment | D80: % Bank Debt Coverage | E80: Owner Investment | F80: Bank Debt Total
A81: Building | B81: TBD | C81: 0.2 | D81: =1-C81 -> 0.8 | E81: =C81*B81 -> #VALUE! | F81: =D81*B81 -> #VALUE!
A82: Equipment | B82: TBD | C82: 0.2 | D82: =1-C82 -> 0.8 | E82: =C82*B82 -> #VALUE! | F82: =D82*B82 -> #VALUE!
A83: Land | B83: TBD | C83: 0.2 | D83: =1-C83 -> 0.8 | E83: =C83*B83 -> #VALUE! | F83: =D83*B83 -> #VALUE!
A84: Site | B84: TBD | C84: 0.2 | D84: =1-C84 -> 0.8 | E84: =C84*B84 -> #VALUE! | F84: =D84*B84 -> #VALUE!
A85: Soft Costs | B85: TBD | C85: 0.2 | D85: =1-C85 -> 0.8 | E85: =C85*B85 -> #VALUE! | F85: =D85*B85 -> #VALUE!
A86: Project Costs | B86: =SUM(B81:B85) -> 0 | C86: =IFERROR((E86/B86),0) -> 0 | D86: =IFERROR((F86/B86),0) -> 0 | E86: =SUM(E81:E85) -> #VALUE! | F86: =SUM(F81:F85) -> #VALUE!
A87: Bank Debt Allocation
A88: Investment Item | B88: Bank Debt Total | C88: Interest Rate | D88: Term of Loan (In Months) | F88: Monthly Payment
A89: Building | B89: =F81 -> #VALUE! | C89: 0.09 | D89: 240 | F89: =IFERROR(PMT(C89/12,(D89),B89)*-1,0) -> 0
A90: Equipment | B90: =F82 -> #VALUE! | C90: 0.09 | D90: 240 | F90: =IFERROR(PMT(C90/12,(D90),B90)*-1,0) -> 0
A91: Land | B91: =F83 -> #VALUE! | C91: 0.09 | D91: 240 | F91: =IFERROR(PMT(C91/12,(D91),B91)*-1,0) -> 0
A92: Site | B92: =F84 -> #VALUE! | C92: 0.09 | D92: 240 | F92: =IFERROR(PMT(C92/12,(D92),B92)*-1,0) -> 0
A93: Soft Costs | B93: =F85 -> #VALUE! | C93: 0.09 | D93: 240 | F93: =IFERROR(PMT(C93/12,(D93),B93)*-1,0) -> 0
A94: Project Costs | B94: =SUM(B89:B93) -> #VALUE! | F94: =SUM(F89:F93) -> 0
A95: Lease Payments
A96: Leased Items | E96: Monthly Payment
A97: Land
A98: Building | E98: 0
A99: Equipment | E99: 0
A100: Total Lease Payments | E100: =SUM(E97:F99) -> 0

Sheet Pro Forma
A27: Exterior Express Car Wash Pro Forma
E28: Prepared For:
E29: ='Input Form'!B2 -> Evan Dailey
E30: ='Input Form'!B3 -> Express Car Wash
E31: ='Input Form'!B4 -> 0
E32: ='Input Form'!B5 -> 231 MacCorkle Ave SW
E33: ='Input Form'!B6 -> South Charleston, WV 25303
B40: Sonny's Enterprises, LLC, it's affiliates, and subsidiaries make no guarantees, representations, or warranties as to the accuracy of specific forecasts, projections, or predictive statements contained herein. Many factors impact the operation and profitability of a car wash that cannot be predicted or built into financial models and projections. The information provided herein is not intended to replace or serve as a substitute for any legal, real estate, tax, or other professional advice, consultation, or service. You assume any and all risk relying on these projections. Original on file at SONNY'S. This proforma does not include additional volume or income generated from a Monthly Unlimited Program. This proforma cannot account for the population density:# of
B46: market competitors ratio or the shared traffic pattern.
B53: Exterior Express Car Wash Pro Forma
C56: Name | E56: =CustomerName -> Evan Dailey
C57: Company | E57: =CompanyName -> Express Car Wash
C58: Address | E58: =AddressLine1 -> 0
E59: =AddressLine2 -> 231 MacCorkle Ave SW
E60: =AddressLine3 -> South Charleston, WV 25303
B63: BREAK EVEN ANALYSIS
B64: Monthly Wash Volume | I64: Break Even | J64: Year One
I65: =IFERROR((('Input Form'!F94+'Input Form'!E100+'Pro Forma'!I83+'Pro Forma'!I84+'Pro Forma'!I89)/('Pro Forma'!J77*(1-('Pro Forma'!G80+'Pro Forma'!G81+'Pro Forma'!G82+'Pro Forma'!G85+'Pro Forma'!G86+'Pro Forma'!G87+'Pro Forma'!G88+'Pro Forma'!G90+'Pro Forma'!G91)))),0) -> 4042.8113 | J65: ='Input Form'!B75 -> 4906.997
B66: Revenue
B67: On-Line Service Description | F67: Price Per Unit | G67: Percentage of Customers | I67: Average Monthly
I68: Break Even | J68: Year One
B69: =BasicPackage -> Basic Package | F69: ='Input Form'!B19 -> 5 | G69: ='Input Form'!D19 -> 0.65 | I69: =IFERROR((I$65*G69*F69),0) -> 13139.137 | J69: =J$65*F69*G69 -> 15947.74
B70: =MenuPackage1 -> Menu Package #1 | F70: ='Input Form'!B20 -> 10 | G70: ='Input Form'!D20 -> 0.15 | I70: =IFERROR((I$65*G70*F70),0) -> 6064.2169 | J70: =J$65*F70*G70 -> 7360.4955
B71: =MenuPackage2 -> Menu Package #2 | F71: ='Input Form'!B21 -> 15 | G71: ='Input Form'!D21 -> 0.12 | I71: =IFERROR((I$65*G71*F71),0) -> 7277.0603 | J71: =J$65*F71*G71 -> 8832.5946
B72: =MenuPackage3 -> Menu Package #3 | F72: ='Input Form'!B22 -> 20 | G72: ='Input Form'!D22 -> 0.04 | I72: =I$65*G72*F72 -> 3234.249 | J72: =J$65*F72*G72 -> 3925.5976
B73: =MenuPackage4 -> Menu Package #4 | F73: ='Input Form'!B23 -> 25 | G73: ='Input Form'!D23 -> 0.04 | I73: =I$65*G73*F73 -> 4042.8113 | J73: =J$65*F73*G73 -> 4906.997
B74: Total On-Line Revenue | I74: =SUM(I69:I73) -> 33757.474 | J74: =SUM(J69:J73) -> 40973.425
B75: Bank and Credit Card Fees | F75: 0.03 | G75: 0.75 | I75: =-(I74*$F75*$G75) -> -759.54317 | J75: =-(J74*$F75*$G75) -> -921.90206
B76: Total Revenue | I76: =SUM(I74:I75) -> 32997.931 | J76: =SUM(J74:J75) -> 40051.523
B77: Total Revenue Per Car | I77: =IFERROR((I76/I65),0) -> 8.162125 | J77: =J76/(J65+0.000000001) -> 8.162125
B78: Operational Expenses
B79: Expense Description | G79: % of Sales | I79: Break Even | J79: Year 1
B80: Advertisements and Promotions | G80: 0.03 | I80: =$G80*I76 -> 989.93793 | J80: =$G80*J76 -> 1201.5457
B81: Chemical Supplies | G81: =IFERROR((J81/J74),0) -> 0.085226347 | I81: =G81*I76 -> 2812.2931 | J81: =('Input Form'!B75*'Input Form'!D19*'Input Form'!C19)+('Input Form'!B75*'Input Form'!C20*'Input Form'!D20)+('Input Form'!B75*'Input Form'!C21*'Input Form'!D21)+('Input Form'!B75*'Input Form'!C22*'Input Form'!D22)+('Input Form'!B75*'Input Form'!C23*'Input Form'!D23) -> 3492.0154
B82: Customer Claims | G82: 0.01 | I82: =$G82*I76 -> 329.97931 | J82: =$G82*J76 -> 400.51523
B83: Insurance | G83: =IFERROR((I83/I74),0) -> 0.029623069 | I83: 1000 | J83: =I83 -> 1000
B84: Labor | G84: =IFERROR((I84/I74),0) -> 0.63425954 | I84: =J84 -> 21411 | J84: =IFERROR(((('Input Form'!B13-40)*'Input Form'!C13*1.5*52/12*(1+'Input Form'!D13)+(40*'Input Form'!C13*52/12*(1+'Input Form'!D13))+(('Input Form'!B14-40)*'Input Form'!C14*1.5*52/12*(1+'Input Form'!D14))+('Input Form'!C14*40*52/12*(1+'Input Form'!D14))+('Input Form'!B15*'Input Form'!C15*52/12*(1+'Input Form'!D14)))),0) -> 21411
B85: Legal and Professional Fees | G85: 0.01 | I85: =$G85*I76 -> 329.97931 | J85: =$G85*J76 -> 400.51523
B86: Licenses and Taxes | G86: 0.01 | I86: =$G86*I76 -> 329.97931 | J86: =$G86*J76 -> 400.51523
B87: Miscellaneous | G87: 0.015 | I87: =$G87*I76 -> 494.96897 | J87: =$G87*J76 -> 600.77285
B88: Property Repairs and Maintenance | G88: 0.01 | I88: =$G88*I76 -> 329.97931 | J88: =$G88*J76 -> 400.51523
B89: Real Estate Taxes | G89: =IFERROR((I89/I74),0) -> 0.059246139 | I89: 2000 | J89: =I89 -> 2000
B90: Refuse Collection | G90: 0.01 | I90: =$G90*I76 -> 329.97931 | J90: =$G90*J76 -> 400.51523
B91: Utilities - Electric, Water, Phone | G91: 0.08 | I91: =$G91*I76 -> 2639.8345 | J91: =$G91*J76 -> 3204.1218
B92: Total Operational Expense | I92: =SUM(I80:I91) -> 32997.931 | J92: =SUM(J80:J91) -> 34912.032
B93: Net Monthly Operational Cash Flow | I93: =I76-I92 -> 4.976755e-09 | J93: =J76-J92 -> 5139.4912
B105: Exterior Express Car Wash Pro Forma
C108: Name | E108: =CustomerName -> Evan Dailey
C109: Company | E109: =CompanyName -> Express Car Wash
C110: Address | E110: =AddressLine1 -> 0
E111: =AddressLine2 -> 231 MacCorkle Ave SW
E112: =AddressLine3 -> South Charleston, WV 25303
B115: BREAK EVEN ANALYSIS
B116: Investment Item | C116: Total Investment | E116: % Owner Investment | F116: % Bank Debt Coverage | G116: Owner Investment | I116: Bank Debt Total
B117: Building | C117: ='Input Form'!B81 -> TBD | E117: ='Input Form'!C81 -> 0.2 | F117: ='Input Form'!D81 -> 0.8 | G117: ='Input Form'!E81 -> #VALUE! | I117: ='Input Form'!F81 -> #VALUE!
B118: Equipment | C118: ='Input Form'!B82 -> TBD | E118: ='Input Form'!C82 -> 0.2 | F118: ='Input Form'!D82 -> 0.8 | G118: ='Input Form'!E82 -> #VALUE! | I118: ='Input Form'!F82 -> #VALUE!
B119: Land | C119: ='Input Form'!B83 -> TBD | E119: ='Input Form'!C83 -> 0.2 | F119: ='Input Form'!D83 -> 0.8 | G119: ='Input Form'!E83 -> #VALUE! | I119: ='Input Form'!F83 -> #VALUE!
B120: Site | C120: ='Input Form'!B84 -> TBD | E120: ='Input Form'!C84 -> 0.2 | F120: ='Input Form'!D84 -> 0.8 | G120: ='Input Form'!E84 -> #VALUE! | I120: ='Input Form'!F84 -> #VALUE!
B121: Soft Costs | C121: ='Input Form'!B85 -> TBD | E121: ='Input Form'!C85 -> 0.2 | F121: ='Input Form'!D85 -> 0.8 | G121: ='Input Form'!E85 -> #VALUE! | I121: ='Input Form'!F85 -> #VALUE!
B122: Project Costs | C122: ='Input Form'!B86 -> 0 | E122: ='Input Form'!C86 -> 0 | F122: ='Input Form'!D86 -> 0 | G122: ='Input Form'!E86 -> #VALUE! | I122: ='Input Form'!F86 -> #VALUE!
B123: Bank Debt Allocation
B124: Investment Item | C124: Bank Debt Total | E124: Interest Rate | G124: Term of Loan (In Months) | I124: Monthly Payment
B125: Building | C125: ='Input Form'!B89 -> #VALUE! | E125: ='Input Form'!C89 -> 0.09 | G125: ='Input Form'!D89 -> 240 | I125: ='Input Form'!F89 -> 0
B126: Equipment | C126: ='Input Form'!B90 -> #VALUE! | E126: ='Input Form'!C90 -> 0.09 | G126: ='Input Form'!D90 -> 240 | I126: ='Input Form'!F90 -> 0
B127: Land | C127: ='Input Form'!B91 -> #VALUE! | E127: ='Input Form'!C91 -> 0.09 | G127: ='Input Form'!D91 -> 240 | I127: ='Input Form'!F91 -> 0
B128: Site | C128: ='Input Form'!B92 -> #VALUE! | E128: ='Input Form'!C92 -> 0.09 | G128: ='Input Form'!D92 -> 240 | I128: ='Input Form'!F92 -> 0
B129: Soft Costs | C129: ='Input Form'!B93 -> #VALUE! | E129: ='Input Form'!C93 -> 0.09 | G129: ='Input Form'!D93 -> 240 | I129: ='Input Form'!F93 -> 0
B130: Total Debt | C130: ='Input Form'!B94 -> #VALUE! | I130: ='Input Form'!F94 -> 0
B131: Lease Payments
B132: Leased Items | I132: Monthly Payment
B133: Building | I133: ='Input Form'!E97 -> 0
B134: Equipment | I134: ='Input Form'!E98 -> 0
B135: Land | I135: ='Input Form'!E99 -> 0
B136: Total Lease Payments | I136: ='Input Form'!E100 -> 0
B137: Cash Flow Summary | G137: Break Even | I137: Year One
B138: Total Revenue | G138: =I76 -> 32997.931 | I138: =J76 -> 40051.523
B139: Total Operational Expenses | G139: =I92 -> 32997.931 | I139: =J92 -> 34912.032
B140: Net Monthly Operational Cash Flow | G140: =G138-G139 -> 4.976755e-09 | I140: =J93 -> 5139.4912
B141: Less Bank Debt | G141: =I130 -> 0 | I141: =I130 -> 0
B142: Less Lease Payments | G142: =I136 -> 0 | I142: =I136 -> 0
B143: Net Cash Flow Per Month | G143: =G140-G141-G142 -> 4.976755e-09 | I143: =I140-I141-I142 -> 5139.4912
B154: Exterior Express Car Wash Pro Forma
C157: Name | E157: =CustomerName -> Evan Dailey
C158: Company | E158: =CompanyName -> Express Car Wash
C159: Address | E159: =AddressLine1 -> 0
E160: =AddressLine2 -> 231 MacCorkle Ave SW
E161: =AddressLine3 -> South Charleston, WV 25303
B164: CASH FLOW PROJECTIONS - YEAR ONE
B165: Annual Wash Volume | I165: Year One | J165: Percentage of Revenue
I166: ='Input Form'!B74 -> 58883.964
B167: Revenue
B168: On-Line Service Description | F168: Price Per Unit | G168: Percentage of Customers
B169: =BasicPackage -> Basic Package | F169: =BasicPackagePrice -> 5 | G169: ='Input Form'!$D$19 -> 0.65 | I169: =I$166*F169*G169 -> 191372.88 | J169: =IFERROR((I169/I$174),0) -> 0.38922156
B170: =MenuPackage1 -> Menu Package #1 | F170: =MenuPackage1Price -> 10 | G170: ='Input Form'!$D$20 -> 0.15 | I170: =I$166*F170*G170 -> 88325.946 | J170: =IFERROR((I170/I$174),0) -> 0.17964072
B171: =MenuPackage2 -> Menu Package #2 | F171: =MenuPackage2Price -> 15 | G171: ='Input Form'!$D$21 -> 0.12 | I171: =I$166*F171*G171 -> 105991.14 | J171: =IFERROR((I171/I$174),0) -> 0.21556886
B172: =MenuPackage3 -> Menu Package #3 | F172: =MenuPackage3Price -> 20 | G172: ='Input Form'!$D$22 -> 0.04 | I172: =I$166*F172*G172 -> 47107.171 | J172: =IFERROR((I172/I$174),0) -> 0.095808383
B173: =MenuPackage4 -> Menu Package #4 | F173: =MenuPackagePrice4 -> 25 | G173: ='Input Form'!$D$23 -> 0.04 | I173: =I$166*F173*G173 -> 58883.964 | J173: =IFERROR((I173/I$174),0) -> 0.11976048
B174: Total On-Line Revenue | I174: =SUM(I169:I173) -> 491681.1 | J174: =IFERROR((I174/I$174),0) -> 1
B175: Bank and Credit Card Fees | F175: =$F$75 -> 0.03 | G175: =$G$75 -> 0.75 | I175: =-(I174*F175*G175) -> -11062.825 | J175: =IFERROR((I175/I$174),0) -> -0.0225
B176: Total Revenue | I176: =I174+I175 -> 480618.28 | J176: =IFERROR((I176/I$174),0) -> 0.9775
...
